tests/__init__.py
tests/test_black_scholes.py
tests/test_characteristic_function.py
tests/test_heston_model.py
tests/test_montecarlo_pricing.py
tiny_pricing_utils/HestonModel.py
tiny_pricing_utils/__init__.py
tiny_pricing_utils/black_scholes.py
tiny_pricing_utils/characteristic_function.py
tiny_pricing_utils/montecarlo.py
tiny_pricing_utils/montecarlo_pricing.py
tiny_pricing_utils/stock_paths.py
tiny_pricing_utils-1.0.3.dist-info/LICENSE
tiny_pricing_utils-1.0.3.dist-info/METADATA
tiny_pricing_utils-1.0.3.dist-info/WHEEL
tiny_pricing_utils-1.0.3.dist-info/top_level.txt
tiny_pricing_utils-1.0.3.dist-info/RECORD
