Metadata-Version: 2.2
Name: tiny_pricing_utils
Version: 1.0.3
Summary: A set of utility functions for my project
Home-page: https://github.com/MichaelCarloH/Option-Pricing/tree/main/tiny_pricing_utils
Author: Michael Carlo
Author-email: michael.carlo@outlook.it
License: MIT
Classifier: Programming Language :: Python :: 3
Classifier: License :: OSI Approved :: MIT License
Classifier: Operating System :: OS Independent
Requires-Python: >=3.6
License-File: LICENSE
Requires-Dist: numpy
Requires-Dist: scipy
Requires-Dist: matplotlib
Dynamic: author
Dynamic: author-email
Dynamic: classifier
Dynamic: description
Dynamic: description-content-type
Dynamic: home-page
Dynamic: license
Dynamic: requires-dist
Dynamic: requires-python
Dynamic: summary
